mu_pipelines_configuration_provider/__init__.py
mu_pipelines_configuration_provider/absolute_configuration_provider.py
mu_pipelines_configuration_provider/configuration_factory.py
mu_pipelines_configuration_provider/diy_configuration_provider.py
mu_pipelines_configuration_provider/read_config.py
mu_pipelines_configuration_provider-0.1.0.dist-info/entry_points.txt
mu_pipelines_configuration_provider-0.1.0.dist-info/licenses/LICENSE
mu_pipelines_configuration_provider-0.1.0.dist-info/WHEEL
mu_pipelines_configuration_provider-0.1.0.dist-info/METADATA
mu_pipelines_configuration_provider-0.1.0.dist-info/RECORD
