Metadata-Version: 2.4
Name: mu_pipelines_configuration_provider
Version: 0.1.0
Summary: mu_pipelines_configuration_provider
Keywords: data movement,spark,etl
Author-email: MosaicSoft <mupipelines@gmail.com>
Requires-Python: >=3.12
Classifier: Programming Language :: Python :: 3
License-File: LICENSE
Requires-Dist: mu-pipelines-interfaces >=0.1.4
